Metadata-Version: 1.0
Name: str-udacity-distributions
Version: 0.2
Summary: Gaussian distributions
Home-page: https://github.com/torinrettig/udacity_distributions
Author: Torin Rettig
Author-email: torin.rettig@gmail.com
License: UNKNOWN
Platform: UNKNOWN
